{
  "id": "contrato_compra_venda",
  "title": "Compromisso de Compra e Venda de Imóvel",
  "fields": [
    { "id": "nome_vendedor", "label": "Nome do Vendedor", "type": "text", "required": true },
    { "id": "cpf_vendedor", "label": "CPF do Vendedor", "type": "cpf", "required": true },
    { "id": "endereco_vendedor", "label": "Endereço do Vendedor", "type": "text", "required": true },
    { "id": "nome_comprador", "label": "Nome do Comprador", "type": "text", "required": true },
    { "id": "cpf_comprador", "label": "CPF do Comprador", "type": "cpf", "required": true },
    { "id": "endereco_comprador", "label": "Endereço do Comprador", "type": "text", "required": true },
    { "id": "descricao_imovel", "label": "Descrição do Imóvel (tipo, área, localização, confrontações)", "type": "multiline", "required": true },
    { "id": "valor_venda", "label": "Valor da Venda (ex: 35.000,00)", "type": "currency", "required": true },
    { "id": "forma_pagamento", "label": "Forma de Pagamento", "type": "text", "required": true },
    { "id": "local_assinatura", "label": "Local de Assinatura", "type": "text", "required": true },
    { "id": "data_assinatura", "label": "Data de Assinatura", "type": "date", "required": true }
  ],
  "template": "COMPROMISSO DE COMPRA E VENDA DE IMÓVEL\n\nPelo presente compromisso de Compra e Venda de imóvel, de um lado {{nome_vendedor}}, brasileiro(a), maior, portador(a) do CPF: {{cpf_vendedor}}, residente e domiciliado(a) em {{endereco_vendedor}}, doravante chamado(a) de VENDEDOR(A), e do outro lado {{nome_comprador}}, brasileiro(a), maior, portador(a) do CPF: {{cpf_comprador}}, residente e domiciliado(a) em {{endereco_comprador}}, doravante chamado(a) de COMPRADOR(A), firmam o presente instrumento conforme as cláusulas seguintes:\n\n[CLAUSULA] DO IMÓVEL OBJETO DA VENDA\n\nO(A) VENDEDOR(A), legítimo(a) possuidor(a) do seguinte imóvel:\n\n{{descricao_imovel}}\n\nresolve, por livre e espontânea vontade, vender o referido imóvel ao(à) COMPRADOR(A), conforme as condições e cláusulas seguintes.\n\n[CLAUSULA] DO PREÇO E CONDIÇÕES DE PAGAMENTO\n\nO preço do imóvel é de R$ {{valor_venda}}, pago {{forma_pagamento}}, de cujo recebimento o(a) VENDEDOR(A) dá plena e geral quitação, obrigando a si e seus herdeiros e sucessores legais ao cumprimento integral deste instrumento.\n\n[CLAUSULA] DA TRANSFERÊNCIA DE POSSE E DOMÍNIO\n\nO(A) VENDEDOR(A), neste ato, transfere ao(à) COMPRADOR(A) o direito de posse legal sobre o imóvel, podendo o(a) mesmo(a) vender, trocar, doar, usufruir ou dispor da forma que melhor lhe convier, sem impedimento algum por parte do(a) VENDEDOR(A) ou de seus sucessores.\n\nPor estarem justos e acordados, VENDEDOR(A) e COMPRADOR(A) assinam o presente instrumento em igual forma e teor, juntamente com as testemunhas abaixo identificadas.\n\n{{local_assinatura}}, {{data_assinatura}}.\n\n______________________________________________\n{{nome_vendedor}}\nCPF: {{cpf_vendedor}}\n\n______________________________________________\n{{nome_comprador}}\nCPF: {{cpf_comprador}}\n\nTESTEMUNHAS\n______________________________________________\nTestemunha 1\n\n______________________________________________\nTestemunha 2"
}
